Workbook

Sheet Datos
B2: Dashboard de Finanzas Personales — Datos
B3: Datos organizados y limpios: enero a junio de 2026
B5: Fecha | C5: Mes | D5: Tipo | E5: Categoría | F5: Descripción | G5: Monto
B6: 46023 | C6: Enero | D6: Ingreso | E6: Ingresos | F6: Salario | G6: 3200000
B7: 46025 | C7: Enero | D7: Gasto | E7: Entretenimiento | F7: Cine | G7: 195736
B8: 46026 | C8: Enero | D8: Gasto | E8: Vivienda | F8: Administración | G8: 200881
B9: 46028 | C9: Enero | D9: Gasto | E9: Salud | F9: Gimnasio | G9: 210099
B10: 46029 | C10: Enero | D10: Gasto | E10: Servicios | F10: Energía | G10: 206401
B11: 46031 | C11: Enero | D11: Gasto | E11: Vivienda | F11: Administración | G11: 111070
B12: 46033 | C12: Enero | D12: Gasto | E12: Alimentación | F12: Domicilio comida | G12: 189273
B13: 46034 | C13: Enero | D13: Gasto | E13: Vivienda | F13: Administración | G13: 175649
B14: 46036 | C14: Enero | D14: Gasto | E14: Alimentación | F14: Mercado | G14: 113705
B15: 46050 | C15: Enero | D15: Gasto | E15: Transporte | F15: Otros gastos | G15: 47186
B16: 46054 | C16: Febrero | D16: Ingreso | E16: Ingresos | F16: Salario | G16: 3200000
B17: 46056 | C17: Febrero | D17: Gasto | E17: Alimentación | F17: Domicilio comida | G17: 125904
... B94: 46196 | C94: Junio | D94: Gasto | E94: Servicios | F94: Internet | G94: 178211

Sheet Fórmulas
B2: Fórmulas automatizadas
B3: Estas celdas alimentan el Dashboard; se recalculan solas si cambian los datos.
B5: Indicador | C5: Valor
B6: Total ingresos | C6: =SUMIF(Datos!$D$6:$D$94,"Ingreso",Datos!$G$6:$G$94) -> 19800000
B7: Total gastos | C7: =SUMIF(Datos!$D$6:$D$94,"Gasto",Datos!$G$6:$G$94) -> 9946566
B8: Balance (ingresos - gastos) | C8: =C6-C7 -> 9853434
B11: Gasto por categoría
B12: Categoría | C12: Total
B13: Alimentación | C13: =SUMIF(Datos!$E$6:$E$94,B13,Datos!$G$6:$G$94) -> 1546119
B14: Transporte | C14: =SUMIF(Datos!$E$6:$E$94,B14,Datos!$G$6:$G$94) -> 1435343
B15: Vivienda | C15: =SUMIF(Datos!$E$6:$E$94,B15,Datos!$G$6:$G$94) -> 1401248
B16: Servicios | C16: =SUMIF(Datos!$E$6:$E$94,B16,Datos!$G$6:$G$94) -> 2261192
B17: Entretenimiento | C17: =SUMIF(Datos!$E$6:$E$94,B17,Datos!$G$6:$G$94) -> 1636704
B18: Salud | C18: =SUMIF(Datos!$E$6:$E$94,B18,Datos!$G$6:$G$94) -> 1665960
B20: Categoría con mayor gasto | C20: =INDEX($B$13:$B$18,MATCH(MAX($C$13:$C$18),$C$13:$C$18,0)) -> Servicios
B23: Resumen mensual
B24: Mes | C24: Ingresos | D24: Gastos | E24: Balance | F24: N° mes
B25: Enero | C25: =SUMIFS(Datos!$G$6:$G$94,Datos!$D$6:$D$94,"Ingreso",Datos!$C$6:$C$94,B25) -> 3200000 | D25: =SUMIFS(Datos!$G$6:$G$94,Datos!$D$6:$D$94,"Gasto",Datos!$C$6:$C$94,B25) -> 1450000 | E25: =C25-D25 -> 1750000 | F25: 1
B26: Febrero | C26: =SUMIFS(Datos!$G$6:$G$94,Datos!$D$6:$D$94,"Ingreso",Datos!$C$6:$C$94,B26) -> 3400000 | D26: =SUMIFS(Datos!$G$6:$G$94,Datos!$D$6:$D$94,"Gasto",Datos!$C$6:$C$94,B26) -> 1520000 | E26: =C26-D26 -> 1880000 | F26: 2
B27: Marzo | C27: =SUMIFS(Datos!$G$6:$G$94,Datos!$D$6:$D$94,"Ingreso",Datos!$C$6:$C$94,B27) -> 3200000 | D27: =SUMIFS(Datos!$G$6:$G$94,Datos!$D$6:$D$94,"Gasto",Datos!$C$6:$C$94,B27) -> 1610000 | E27: =C27-D27 -> 1590000 | F27: 3
B28: Abril | C28: =SUMIFS(Datos!$G$6:$G$94,Datos!$D$6:$D$94,"Ingreso",Datos!$C$6:$C$94,B28) -> 3400000 | D28: =SUMIFS(Datos!$G$6:$G$94,Datos!$D$6:$D$94,"Gasto",Datos!$C$6:$C$94,B28) -> 1690000 | E28: =C28-D28 -> 1710000 | F28: 4
B29: Mayo | C29: =SUMIFS(Datos!$G$6:$G$94,Datos!$D$6:$D$94,"Ingreso",Datos!$C$6:$C$94,B29) -> 3200000 | D29: =SUMIFS(Datos!$G$6:$G$94,Datos!$D$6:$D$94,"Gasto",Datos!$C$6:$C$94,B29) -> 1780000 | E29: =C29-D29 -> 1420000 | F29: 5
B30: Junio | C30: =SUMIFS(Datos!$G$6:$G$94,Datos!$D$6:$D$94,"Ingreso",Datos!$C$6:$C$94,B30) -> 3400000 | D30: =SUMIFS(Datos!$G$6:$G$94,Datos!$D$6:$D$94,"Gasto",Datos!$C$6:$C$94,B30) -> 1896566 | E30: =C30-D30 -> 1503434 | F30: 6
B32: Proyección de gasto — Julio (FORECAST) | C32: =FORECAST(7,$D$25:$D$30,$F$25:$F$30) -> 1967044

Sheet Dashboard
B2: Dashboard — Control de Finanzas Personales
B3: Se actualiza automáticamente al cambiar los datos de la hoja 'Datos'
B5: TOTAL INGRESOS | D5: TOTAL GASTOS | F5: BALANCE | H5: PROYECCIÓN JULIO
B6: =Fórmulas!C6 -> 19800000 | D6: =Fórmulas!C7 -> 9946566 | F6: =Fórmulas!C8 -> 9853434 | H6: =Fórmulas!C32 -> 1967044
B9: Categoría con mayor gasto: | D9: =Fórmulas!C20 -> Servicios
B46: Nota: para segmentar el dashboard de forma interactiva (por mes o categoría) desde Excel, selecciona los datos de 'Datos' → Insertar → Tabla dinámica, y luego Insertar → Segmentación de datos. Este archivo deja las fórmulas y gráficos listos como base.

Sheet Documentación
B2: Documentación del Proyecto Final
B4: Problema
B5: Necesidad de controlar y proyectar las finanzas personales mes a mes: saber cuánto ingresa, cuánto se gasta, en qué categorías, y anticipar el próximo mes.
B7: Fuente de datos
B8: Registro propio de transacciones (enero–junio 2026), limpio y estandarizado en la hoja 'Datos' con columnas Fecha, Mes, Tipo, Categoría, Descripción y Monto.
B10: Herramientas y fórmulas usadas
B11: SUMIF / SUMIFS para totales por tipo, categoría y mes. INDEX + MATCH + MAX para identificar la categoría con mayor gasto. FORECAST (función predictiva) para proyectar el gasto de julio. Gráficos de barras, líneas y pastel enlazados por fórmula al motor de cálculo de la hoja 'Fórmulas'.
B13: Dashboard
B14: La hoja 'Dashboard' resume 4 indicadores clave (ingresos, gastos, balance, proyección) y 3 visualizaciones (gasto por categoría, ingresos vs. gastos por mes, distribución del gasto). Todo se recalcula automáticamente al cambiar los datos.
B16: Conclusiones
B17: El balance mensual es positivo pero se estrecha porque el gasto crece más rápido que el ingreso. 'Vivienda' y 'Transporte' concentran la mayor parte del gasto. La proyección para julio sugiere reforzar el control de presupuesto si la tendencia continúa.
